README.txt
setup.cfg
setup.py
collective/__init__.py
collective.geo.geopoint.egg-info/PKG-INFO
collective.geo.geopoint.egg-info/SOURCES.txt
collective.geo.geopoint.egg-info/dependency_links.txt
collective.geo.geopoint.egg-info/entry_points.txt
collective.geo.geopoint.egg-info/namespace_packages.txt
collective.geo.geopoint.egg-info/not-zip-safe
collective.geo.geopoint.egg-info/requires.txt
collective.geo.geopoint.egg-info/top_level.txt
collective/geo/__init__.py
collective/geo/geopoint/README.txt
collective/geo/geopoint/__init__.py
collective/geo/geopoint/config.py
collective/geo/geopoint/configure.zcml
collective/geo/geopoint/geopoint.py
collective/geo/geopoint/geopointform.pt
collective/geo/geopoint/geopointform.py
collective/geo/geopoint/geopointmacros.pt
collective/geo/geopoint/interfaces.py
collective/geo/geopoint/schema.py
collective/geo/geopoint/tests.py
collective/geo/geopoint/version.txt
collective/geo/geopoint/locales/collective.geo.geopoint.pot
collective/geo/geopoint/locales/rebuild.sh
collective/geo/geopoint/locales/it/LC_MESSAGES/collective.geo.geopoint.mo
collective/geo/geopoint/locales/it/LC_MESSAGES/collective.geo.geopoint.po
docs/HISTORY.txt
docs/INSTALL.txt
docs/LICENSE.GPL
docs/LICENSE.txt