Metadata-Version: 1.0
Name: collective.geo.geopoint
Version: 0.1
Summary: z3c.form geopoint field support
Home-page: https://svn.plone.org/svn/collective/collective.geo.geopoint
Author: Giorgio Borelli
Author-email: giorgio@giorgioborelli.it
License: GPL
Platform: UNKNOWN
Classifier: Framework :: Plone
Classifier: Programming Language :: Python
Classifier: Topic :: Software Development :: Libraries :: Python Modules
